LICENSE
MANIFEST.in
README.md
requirements.txt
setup.cfg
setup.py
metasam/__init__.py
metasam/demo.py
metasam.egg-info/PKG-INFO
metasam.egg-info/SOURCES.txt
metasam.egg-info/dependency_links.txt
metasam.egg-info/requires.txt
metasam.egg-info/top_level.txt
metasam/sam2/__init__.py
metasam/sam2/automatic_mask_generator.py
metasam/sam2/build_sam.py
metasam/sam2/sam2_image_predictor.py
metasam/sam2/sam2_video_predictor.py
metasam/sam2/csrc/connected_components.cu
metasam/sam2/modeling/__init__.py
metasam/sam2/modeling/memory_attention.py
metasam/sam2/modeling/memory_encoder.py
metasam/sam2/modeling/position_encoding.py
metasam/sam2/modeling/sam2_base.py
metasam/sam2/modeling/sam2_utils.py
metasam/sam2/modeling/backbones/__init__.py
metasam/sam2/modeling/backbones/hieradet.py
metasam/sam2/modeling/backbones/image_encoder.py
metasam/sam2/modeling/backbones/utils.py
metasam/sam2/modeling/sam/__init__.py
metasam/sam2/modeling/sam/mask_decoder.py
metasam/sam2/modeling/sam/prompt_encoder.py
metasam/sam2/modeling/sam/transformer.py
metasam/sam2/utils/__init__.py
metasam/sam2/utils/amg.py
metasam/sam2/utils/misc.py
metasam/sam2/utils/transforms.py
metasam/sam2_configs/__init__.py