Metadata-Version: 2.1
Name: metasam
Version: 0.0.2
Summary: Metasam A Python package for Inference SAM
Home-page: https://github.com/kadirnar/metasam
Author: kadirnar
Author-email: kadir.nar@hotmail.com
License: Apache License 2.0
License-File: LICENSE
Requires-Dist: transformers
Requires-Dist: huggingface-hub
Requires-Dist: bitsandbytes
Requires-Dist: accelerate
Requires-Dist: jinja2>=3.1.0
Requires-Dist: peft
